{
  "type": "FeatureCollection",
  "features": [
    {
      "type": "Feature",
      "properties": {
        "name": "Sozina tunel",
        "gate": "g1"
      },
      "geometry": {
        "type": "Polygon",
        "coordinates": [
          [
            [
              19.049938917160034,
              42.20192190597213
            ],
            [
              19.049938917160034,
              42.2033127432949
            ],
            [
              19.05177354812622,
              42.2033127432949
            ],
            [
              19.05177354812622,
              42.20192190597213
            ],
            [
              19.049938917160034,
              42.20192190597213
            ]
          ]
        ]
      }
    },
    {
      "type": "Feature",
      "properties": {
        "name": "A2",
        "gate": "g1"
      },
      "geometry": {
        "type": "Polygon",
        "coordinates": [
          [
            [
              28.01466464996338,
              44.33895137497899
            ],
            [
              28.01466464996338,
              44.34025584767261
            ],
            [
              28.017067909240723,
              44.34025584767261
            ],
            [
              28.017067909240723,
              44.33895137497899
            ],
            [
              28.01466464996338,
              44.33895137497899
            ]
          ]
        ]
      }
    },
    {
      "type": "Feature",
      "properties": {
        "name": "DN2A",
        "gate": "g1"
      },
      "geometry": {
        "type": "Polygon",
        "coordinates": [
          [
            [
              27.87205696105957,
              44.752097396080465
            ],
            [
              27.87205696105957,
              44.75618113546708
            ],
            [
              27.880382537841797,
              44.75618113546708
            ],
            [
              27.880382537841797,
              44.752097396080465
            ],
            [
              27.87205696105957,
              44.752097396080465
            ]
          ]
        ]
      }
    }
  ]
}